{
  "url": "https://cryptopanic.com/news/dogecoin/",
  "unique_key": "https://cryptopanic.com/news/dogecoin",
  "method": "GET",
  "headers": {},
  "payload": null,
  "user_data": {
    "__crawlee": {
      "state": 3,
      "crawlDepth": 1
    }
  },
  "retry_count": 0,
  "no_retry": false,
  "loaded_url": "https://cryptopanic.com/news/dogecoin/",
  "handled_at": "2024-12-23 03:48:12.095182+00:00",
  "id": "Pzp5BgGUmGKK4Gm",
  "json_": "{\n  \"url\": \"https://cryptopanic.com/news/dogecoin/\",\n  \"unique_key\": \"https://cryptopanic.com/news/dogecoin\",\n  \"method\": \"GET\",\n  \"headers\": {},\n  \"payload\": null,\n  \"user_data\": {\n    \"__crawlee\": {\n      \"state\": 3,\n      \"crawlDepth\": 1\n    }\n  },\n  \"retry_count\": 0,\n  \"no_retry\": false,\n  \"loaded_url\": \"https://cryptopanic.com/news/dogecoin/\",\n  \"handled_at\": \"2024-12-23 03:48:12.095182+00:00\",\n  \"id\": \"Pzp5BgGUmGKK4Gm\",\n  \"order_no\": null\n}",
  "order_no": null
}